commitai/__init__.py
commitai/cli.py
commitai/git.py
commitai/template.py
commitai-1.0.5.dist-info/METADATA
commitai-1.0.5.dist-info/WHEEL
commitai-1.0.5.dist-info/entry_points.txt
commitai-1.0.5.dist-info/licenses/LICENSE
commitai-1.0.5.dist-info/RECORD
