Metadata-Version: 2.4
Name: commitai
Version: 1.0.5
Summary: Commitai helps you generate git commit messages using AI
Project-URL: Bug Tracker, https://github.com/lguibr/commitai/issues
Project-URL: Documentation, https://github.com/lguibr/commitai/blob/main/README.md
Project-URL: Source Code, https://github.com/lguibr/commitai
Author-email: Luis Guilherme <lgpelin92@gmail.com>
License: # File: LICENSE
License-File: LICENSE
Classifier: Development Status :: 4 - Beta
Classifier: Intended Audience :: Developers
Classifier: License :: OSI Approved :: MIT License
Classifier: Operating System :: OS Independent
Classifier: Programming Language :: Python :: 3
Classifier: Programming Language :: Python :: 3.9
Classifier: Programming Language :: Python :: 3.10
Classifier: Programming Language :: Python :: 3.11
Classifier: Programming Language :: Python :: 3.12
Classifier: Topic :: Software Development :: Version Control :: Git
Classifier: Topic :: Utilities
Requires-Python: >=3.9
Requires-Dist: click<9.0,>=8.0
Requires-Dist: langchain-anthropic<=0.3.12,>=0.1.0
Requires-Dist: langchain-community<=0.3.23,>=0.0.20
Requires-Dist: langchain-core<=0.3.58,>=0.1.0
Requires-Dist: langchain-google-genai~=2.1.4
Requires-Dist: langchain-ollama~=0.3.2
Requires-Dist: langchain-openai<=0.3.16,>=0.1.0
Requires-Dist: langchain<=0.3.25,>=0.1.0
Requires-Dist: pydantic<3.0,>=2.0
Provides-Extra: test
Requires-Dist: langchain-google-genai~=2.1.4; extra == 'test'
Requires-Dist: mypy>=1.9.0; extra == 'test'
Requires-Dist: pytest-cov>=3.0; extra == 'test'
Requires-Dist: pytest>=7.0; extra == 'test'
Requires-Dist: ruff==0.4.4; extra == 'test'
Requires-Dist: types-setuptools; extra == 'test'
